client/__init__.py
client/add_contact.py
client/client.py
client/database.py
client/del_contact.py
client/main_window.py
client/main_window_conv.py
client/start_dialog.py
client/transport.py
my_first_messenger_client-0.1.dist-info/METADATA
my_first_messenger_client-0.1.dist-info/WHEEL
my_first_messenger_client-0.1.dist-info/top_level.txt
my_first_messenger_client-0.1.dist-info/RECORD
