Metadata-Version: 2.1
Name: my-first-messenger-client
Version: 0.1
Summary: Messenger Client
Home-page: UNKNOWN
Author: Zakharov Vladimir
Author-email: vovazakharov2@gmail.com
License: UNKNOWN
Platform: UNKNOWN
Requires-Dist: PyQt5
Requires-Dist: sqlalchemy
Requires-Dist: pycryptodome
Requires-Dist: pycryptodomex
